LICENSE.txt
README.md
README.txt
pyproject.toml
setup.py
src/downsample/__init__.py
src/downsample/_ltd.c
src/downsample/_ltd.pyi
src/downsample/_ltob.c
src/downsample/_ltob.pyi
src/downsample/_lttb.c
src/downsample/_lttb.pyi
src/downsample/py.typed
src/downsample/utils.c
src/downsample/utils.h
src/downsample.egg-info/PKG-INFO
src/downsample.egg-info/SOURCES.txt
src/downsample.egg-info/dependency_links.txt
src/downsample.egg-info/requires.txt
src/downsample.egg-info/top_level.txt
src/downsample/tests/__init__.py
src/downsample/tests/test_ltd.py
src/downsample/tests/test_ltob.py
src/downsample/tests/test_lttb.py
src/examples/__init__.py
src/examples/plot.py
src/examples/spikydata.py