Metadata-Version: 2.1
Name: downsample
Version: 0.0.5
Summary: Downsample algorithms module for Python written in C
Author-email: Dennis Göries <dennis@goeries.de>
Maintainer-email: Dennis Göries <dennis@goeries.de>
License: MIT
Project-URL: git, https://github.com/dgoeries/downsample
Classifier: Development Status :: 4 - Beta
Classifier: Environment :: Console
Classifier: Intended Audience :: Developers
Classifier: Intended Audience :: Science/Research
Classifier: License :: OSI Approved :: MIT License
Classifier: Operating System :: OS Independent
Classifier: Programming Language :: Python :: 3
Classifier: Programming Language :: Python :: Implementation :: CPython
Classifier: Topic :: Scientific/Engineering :: Information Analysis
Classifier: Topic :: Scientific/Engineering :: Physics
Classifier: Topic :: Scientific/Engineering :: Visualization
Requires-Python: >=3.10
License-File: LICENSE.txt
Requires-Dist: numpy>=2.0
